treegenix/__init__.py
treegenix/__main__.py
treegenix-0.1.2.dist-info/LICENSE
treegenix-0.1.2.dist-info/METADATA
treegenix-0.1.2.dist-info/WHEEL
treegenix-0.1.2.dist-info/entry_points.txt
treegenix-0.1.2.dist-info/top_level.txt
treegenix-0.1.2.dist-info/RECORD
