Metadata-Version: 2.1
Name: treegenix
Version: 0.1.2
Summary: A Python CLI tool to generate directory tree structures
Home-page: https://github.com/sujal-1245/treegenix.git
Author: Sujal Bhagat
Author-email: sujaldbhagat2004@gmail.com
License: MIT
Classifier: Development Status :: 3 - Alpha
Classifier: Intended Audience :: Developers
Classifier: License :: OSI Approved :: MIT License
Classifier: Programming Language :: Python :: 3
Classifier: Environment :: Console
Classifier: Operating System :: OS Independent
Classifier: Topic :: Utilities
Requires-Python: >=3.6
License-File: LICENSE
